mystenlabs-0.1.0.dist-info/METADATA
mystenlabs-0.1.0.dist-info/WHEEL
mystenlabs-0.1.0.dist-info/licenses/LICENSE
mystenlabs/__init__.py
mystenlabs/mystenlabs.cpython-313-darwin.so
mystenlabs-0.1.0.dist-info/RECORD
